AUTHORS
CHANGES.rst
LICENSE
MANIFEST.in
README.rst
setup.py
coffeescript/__init__.py
coffeescript/cache.py
coffeescript/finders.py
coffeescript/models.py
coffeescript/settings.py
coffeescript/storage.py
coffeescript/templatetags/__init__.py
coffeescript/templatetags/coffeescript.py
coffeescript/tests/__init__.py
coffeescript/tests/django_settings.py
coffeescript/tests/tests.py
django_coffeescript.egg-info/PKG-INFO
django_coffeescript.egg-info/SOURCES.txt
django_coffeescript.egg-info/dependency_links.txt
django_coffeescript.egg-info/top_level.txt