Metadata-Version: 1.0
Name: django-coffeescript
Version: 0.7.1
Summary: Django template tags to compile CoffeeScript
Home-page: https://github.com/andreyfedoseev/django-coffeescript
Author: Andrey Fedoseev
Author-email: andrey.fedoseev@gmail.com
License: UNKNOWN
Keywords: coffeescript
Platform: UNKNOWN
Classifier: Development Status :: 4 - Beta
Classifier: Framework :: Django
Classifier: Intended Audience :: Developers
Classifier: License :: OSI Approved :: BSD License
Classifier: Operating System :: OS Independent
Classifier: Programming Language :: Python
Classifier: Topic :: Internet :: WWW/HTTP
